mindsdb_text_to_sql/__about__.py
mindsdb_text_to_sql/__init__.py
mindsdb_text_to_sql/gpt.py
mindsdb_text_to_sql/gpt_text_to_sql.py
mindsdb_text_to_sql/config/examples.json
mindsdb_text_to_sql-0.1.1.dist-info/METADATA
mindsdb_text_to_sql-0.1.1.dist-info/WHEEL
mindsdb_text_to_sql-0.1.1.dist-info/top_level.txt
mindsdb_text_to_sql-0.1.1.dist-info/RECORD
