Metadata-Version: 2.1
Name: mindsdb-text-to-sql
Version: 0.1.1
Summary: MindsDB Text to SQL, converts natural language to SQL code.
Home-page: https://github.com/MinuraPunchihewa/mindsdb-text-to-sql
Author: Minura Punchihewa
Author-email: minurapunchihewa17@gmail.com
License: UNKNOWN
Download-URL: https://pypi.org/project/mindsdb-text-to-sql/
Platform: UNKNOWN
Classifier: Programming Language :: Python :: 3
Classifier: Operating System :: OS Independent
Requires-Python: >=3.7
Requires-Dist: openai
Requires-Dist: python-dotenv
